{
  "arxiv_id": "2205.08382v1",
  "title": "Compatible deep neural network framework with financial time series data, including data preprocessor, neural network model and trading strategy",
  "authors": [
    "Mohammadmahdi Ghahramani",
    "Hamid Esmaeili Najafabadi"
  ],
  "categories": [
    "cs.LG",
    "cs.AI",
    "cs.CE"
  ],
  "published": "2022-05-11T20:44:08Z",
  "summary": "Experience has shown that trading in stock and cryptocurrency markets has the potential to be highly profitable. In this light, considerable effort has been recently devoted to investigate how to apply machine learning and deep learning to interpret and predict market behavior. This research introduces a new deep neural network architecture and a novel idea of how to prepare financial data before feeding them to the model. In the data preparation part, the first step is to generate many features using technical indicators and then apply the XGBoost model for feature engineering. Splitting data into three categories and using separate autoencoders, we extract high-level mixed features at the second step. This data preprocessing is introduced to predict price movements. Regarding modeling, different convolutional layers, an long short-term memory unit, and several fully-connected layers have been designed to perform binary classification. This research also introduces a trading strategy to exploit the trained model outputs. Three different datasets are used to evaluate this method, where results indicate that this framework can provide us with profitable and robust predictions.",
  "pdf_url": "https://arxiv.org/pdf/2205.08382v1",
  "source_query": "feature engineering financial machine learning",
  "pdf_path": "./arxiv_papers/pdfs/2205.08382v1.pdf",
  "text": "Compatible deep neural network framework with financial\ntime series data, including data preprocessor, neural network\nmodel and trading strategy\nMohammadmahdi Ghahramani1Y, Hamid Esmaeili Najafabadi 2‡\n1 Mathematics Department/University of Padova, Padua, Italy\n2 Electrical and Computer Engineering Department/University of Calgary, Calgary,\nCanada\nYmuhammadmahdi0007@gmail.com\n‡hamid.esmaeilinajafa@ucalgary.ca\nAbstract\nExperience has shown that trading in stock and cryptocurrency markets has the\npotential to be highly profitable. In this light, considerable effort has been recently\ndevoted to investigate how to apply machine learning and deep learning to interpret and\npredict market behavior. This research introduces a new deep neural network\narchitecture and a novel idea of how to prepare financial data before feeding them to\nthe model. In the data preparation part, the first step is to generate many features\nusing technical indicators and then apply the XGBoost model for feature engineering.\nSplitting data into three categories and using separate autoencoders, we extract\nhigh-level mixed features at the second step. This data preprocessing is introduced to\npredict price movements. Regarding modeling, different convolutional layers, an long\nshort-term memory unit, and several fully-connected layers have been designed to\nperform binary classification. This research also introduces a trading strategy to exploit\nthe trained model outputs. Three different datasets are used to evaluate this method,\nwhere results indicate that this framework can provide us with profitable and robust\npredictions.\nIntroduction\nActing on cryptocurrency and stock markets has recently gained a great deal of\npopularity. People’s curiosity about financial keywords such as Bitcoin (BTC),\nEthereum (ETH), Tether (USDT), cryptocurrency, technical analysis, etc., has\nincreased significantly. There has been a 200 percent increase in this interest for some\nAsian countries during the last year as per google trends data. Apart from people’s\nwillingness, researchers have also been seeking to develop efficient methods to deal with\nthe complexity of financial markets. Focusing more on modeling, a significant number of\nstudies were conducted on how to predict the price movement direction using machine\nlearning algorithms and deep neural networks (DNNs). Thanks to advances in neural\nnetworks, the dream of forecasting financial time series is now much closer to reality.\nGenerally speaking, when it comes to financial data, there are two main problems we\nshould address. The first one is to introduce robust features through which the market\ncan be correctly represented [1] and the second one is market complexity and\nvolatility [2]. Because of market elements’ nonlinear relationships [3–5], it is not\nMay 18, 2022 1/26\narXiv:2205.08382v1  [cs.LG]  11 May 2022\nsurprising deep neural networks are used a lot to predict market fluctuations. They vary\nfrom using fully-connected neural networks [6] to taking advantage of convolutional\nneural networks (CNNs) [7–10], recurrent neural networks (RNNs) [2,11] and long\nshort-term memory (LSTM) [12 –14]. However, the critical point would be that instead\nof spending too much time designing complex neural network architectures, we should\nequally care about modeling and extracting valuable features.\nThis study is divided into two parts: data preparation and modeling. This research\ntries to provide intuition for each step to make it closer to what is happening in the\nstock or cryptocurrency markets.\nFeature generation (FG), data denoising (DD), feature engineering (FE), data\nsplitting (DS), create representative dataset (CD), and using auto-encoders (AE) are\nconsidered as six crucial steps for the first part. Modeling part also involves\nconvolutional layers, LSTM units, and fully-connected layers for binary classification.\nSince the concern of robustness in financial tasks has always been an issue, the\nperformance of the proposed method is evaluated on three different datasets. They\ninclude four-hour data of BTC and ETH coins from the cryptocurrency market and\ndaily data for the S&P500 index.\nFor a trader, it is imperative to use technical analysis according to the current\nmarket state correctly. Traders cannot afford to use only one specific indicator from\nwhich they might have continuously gained profit, e.g., exponentially moving average\n(EMA). Although it may have brought them significant profit in one of the market\nstates, it immediately loses its performance as the market state changes. They also need\nto utilize other tools, such as price channels or other indicators like relative strength\nindex (RSI). It is indeed the unique quality distinguishing amateur traders from\nprofessionals. Taking advantage of this intuition, it is quickly unfolded that feature\nengineering should be dynamic. Gathering a set of features to represent all or most\ncorresponding states not only for different markets but also for different seasons of the\nsingle market is critical. In this light, we first generate numerous potential features from\nopen, high, low, close prices and volume data (OHLCV) to design a dynamic feature\nextractor. Then, we apply a wavelet transformer to denoise the generated\nfeatures [5,15]. Finally, feature engineering is applied to generated features since the\nimportance levels of these features are still unknown [16].\nNeural network models are notably susceptible to features quality. If they are fed\nwith low-quality features, their performance is less likely to be as desired. Here, the idea\nof using auto-encoders is introduced to ensure that only high-quality features are fed to\nour primary model. They have been used in other studies to extract both high-quality\nfeatures [5] and data denoising [17]. However, the approach used in this paper is totally\ndifferent from these studies since we designed customized CNN-based auto-encoders [18]\nand used two auto-encoders instead of one. An auto-encoder aims to learn a compressed,\ndistributed representation for a dataset or reduce data dimensionality. It can give us the\nedge to make the proposed model work better. Auto-encoder’s performance depends on\nfeature correlation such that a higher degree of correlation between the input features\nboosts the auto-encoder’s performance. When it comes to financial markets, features are\nnot necessarily correlated enough. Hence, feeding them all directly into an auto-encoder\nwould not result in extracting high-quality features. To address this challenge, we\nconsider the data splitting step. Before feeding these splitted data to separate\nauto-encoders, it is worth deliberating on how traders are trading and whether they only\nlook at one single candle or they tend to review the price path when deciding to buy or\nsell. This intuition tells us a single candle should not be considered a training instance\nbut instead their trend. In this light, a new dataset is created in step CD, where candle\nsets are considered training instances. The data is now ready to be fed to auto-encoders.\nThe rest of this paper is about designing a neural network-based architecture to\nMay 18, 2022 2/26\nbinary-classify the prepared data coming from the preparation part. Even though some\nstudies attempted to predict the value of price directly using regression methods and\nthen define a trading strategy to exploit results [5], it seems it would be more efficient\nand closer to reality to predict the price movement direction instead of the price value.\nThis paper considers a trading strategy part that determines how this model should\nbe applied in our financial activities to exploit our model outputs efficiently. This part\nhas been rarely considered in other studies. It is precisely why they mainly can not be\nused by organizations and traders to earn profit from financial markets. It first explains\nseveral unrealistic assumptions which may make us wrongly evaluate our model and\nthen suggests intuitive solutions to address them. Secondly, it talks about indexes to\ncorrectly assess the model because coming up with a highly accurate model does not\nnecessarily result in earning profit from the trading system [12]. In contrast, none of all\nlow-accurate models are useless.\nRelated works\nHaving access to the high performance GPUs and hardware along with advances in deep\nlearning and machine learning, the opportunity to utilize all deep learning methods and\ntechniques has been provided for researchers. Consequently, standard deep learning\nmethods that are typically used in specific areas have been tested on financial time\nseries data. J Vahala et al. [6] review the performance of fully-connected layers to\npredict financial markets. Focusing on feature extraction, Xiao Ding et al. [19] use a\ndeep convolutional network to improve prediction accuracy. Using the same concept, Jia\nWang et al. [7] propose one-dimensional convolutional neural networks with the aim of\nmarket movement forecasting. With respect to the nature of financial data, RNNs and\nLSTM units are also widely used. Using these networks, Razvan Zanc et al. [12]\nconclude that accuracy is not a good indicator to evaluate the model profitability, and\nhigh values of accuracy may not contribute positively to a profitable trading system. In\nanother paper, Avraam Tsantekidis et al. [2] attempt to exploit RNNs on time-series\ndata on limit order books. Justin Sirignano et al. [20], mark that there is\npath-dependence in price dynamics. Wei Bao et al. [5] utilize stacked auto-encoders in\nthe combination of LSTM units to predict one-step-ahead close price . In another work\nby Ali Caner T¨ urkmen et al. [17], an array of features are generated, and the\nperformance of several machine learning algorithms are tested.\nEven though various innovative ideas have been implemented in this field, financial\ndata preprocessing and taking advantage of traders’ intuitions are not adequately\nconsidered. This paper covers this topic by considering a dynamic feature engineering\nmethod. In related research, the intuition behind selecting a method for modeling was\nexplained. However, none of them has tried to select the model’s parameters according\nto the common rules in the market and among traders. As the second edge, not only\ndoes this research make an effort to construct an intuitive network, it also suggests\nsetting the network’s parameters intuitively. While the importance of existing a trading\nstrategy is not undeniable by traders, defining a trading strategy is another topic that\nother researchers did not consider. This work also proposes a strategy to turn the\nmodel’s output into profit.\nMay 18, 2022 3/26\nMaterials and methods\n1 Data preparation\nProviding an informative set of data has always played a vital role in machine learning\ntasks. The focus of this part is that gathering and engineering data for the market is as\ncrucial as designing complex neural networks. One of the trader’s primary tools to\nanalyze the price movement is OHLCV data. Interaction between these features helps\nmarket actors to predict upward or downward trends in advance. Based on their\nimportance, we start with a raw dataset including OHLCV data.\n1.1 Feature generation\nFinancial markets are renowned for their complexity [21, 22]. This complexity is coming\nfrom a volatile supply and demand pressure which determines the price. Consequently,\ntraders encounter market states where price behavior is unpredictable since different\ntechnical tools might provide them with opposite signals. This condition gets even more\nchallenging when traders need to struggle with setting hyperparameters for their\ntechnical tools. Consider that it is desired to earn five percent worth of profit by buying\nBitcoin, but there is an uncertainty about whether this is the right time. One possible\napproach is to take a look at the BTC/USDT chart and analyze the price. Then, it\nmust be figured out which set of indicators are better to use. Having done that,\noptimum parameters for the selected indicators should be set. For example, an EMA\nindicator with the window of 21 may provide a better prediction rather than the\nwindow of 35. To take this fact into account, this part generates too many indicators\nwith different parameters whose summary is brought in Table 1. Therefore, the new\ndataset may include several EMA columns, each with its own window. Consequently,\nthe variety in both indicators and parameters is provided.\n1.2 Data denoising\nPeople use exchanges to trade in financial markets. Anyone can trade on them, whether\nthey are professionals or novices. As a result, financial markets get noisier than what\nthey already are. All market activities affect demand and supply pressure and, as a\nresult, price. It is important to consider only transactions that contains information.\nThis research suggests taking the data denoising step. However, handling all kinds of\nnoises in financial markets is impossible.\nThis paper recommends using the wavelet transforms to convert the data to a\nsmoother version of that [23]. Wavelet transformers are widely-used to signal denoising,\nespecially in electrical engineering. Since we can suppose our time-series data like a\nsignal, this transformer can be employed with the aim of denoising [5]. Wavelet analysis\nwas first developed in the early 1980s in seismic signal analysis in the form of an\nintegral transform with a localized kernel function with continuous parameters of\ndilation and translation. They have been applied to various kinds of one-dimensional or\nmultidimensional signals, for example, to identify an event or to denoise the signal.\nApart from data denoising, applying wavelet transforms protects the model against\nover-fitting.\n1.3 Feature engineering\nOne of the most essential steps for every machine learning task is feature engineering.\nFeature engineering is the process of using domain knowledge to extract features from\nraw data. This part cares about transforming raw data into components that better\nMay 18, 2022 4/26\nT able 1. List of some common technical indicators to generate features\nName\nADX\nATR\nBOLL\nCCI\nChaikinAD\nEMA\nGARCH\nMA\nMACD\nMFI\nMOM\nParabolicSAR\nROC\nRSI\nStochastic\nVWMA\nWilder\nWilliams\nIndicators\nEquivalent Description\nAverage directional index\nAverage true range\nBollinger bands\nCommodity channel index\nExponential moving average\nMoving average\nMoney flow index\nMomentum indicator\nRate of change\nRelative strength index\nVolume weighted moving average\nMoving average convergence divergence\nTo determine when the price is trending strongly\nVolatility indicator that shows how much an asset moves\nTwo standard deviations above and below a simple moving average\nDifference between the current and the historical average price\nAnticipate directional changes in the accumulation distribution\nEstimates the volatility of returns for stocks\nTrend following momentum indicator\nUses both price and volume to measure buying and selling pressure\nMeasures a security’s rate of change\nDetermines the direction that an asset is moving\nCalculates the percent change in price between periods\nEvaluates overbought or oversold conditions\nMomentum indicator that uses support and resistance levels\nMeasures a trend’s strength and direction\nMeasures overbought and oversold levels\nTable notes that various indicators and oscillators are considered to cover common approaches\nindeed when analyzing financial markets.\nrepresent the underlying problem to the predictive models, resulting in improved model\naccuracy on unseen data.\nTill now, we generated features and applied wavelet transforms with the aim of\ndenoising. These two basic steps are not adequate to prepare the data. Adding several\nindicators to a price chart is simply the process of feature generation which even\namature traders can do. They may also ignore some upper or lower shadows of candles\nand imagine the smoother version of the chart. Since the mere use of these steps do not\nequip them with robust and dependable forecasting, no wonder if the FG and DD steps\nalone do not give us a significant edge. This part introduces a reliable method to\nextract valuable features. The paper divides the FE step into two sections. The first\none is explained here, and the second one is covered on the auto-encoder part.\nThe market contains different complex states and we must use a dynamic feature\nengineering method to represent them. To design that, this study takes advantage of\nanother intuition. Financial market participants tend to consult with experts and use\ntheir insights before investing in financial markets. In our case, there is a machine\nlearning method whose primary duty is to determine feature importance. This paper\nselects XGBoost classifier [24] to play an expert role since tree-based machine learning\nalgorithms are not sensitive about the quality of every single feature and can ignore\nthose features with a lower information [25]. This feature turns the XGBoost classifier\ninto an excellent candidate to calculate feature importance. Each time it is fed with\nMay 18, 2022 5/26\ndifferent data, feature importance changes. Fig 1 is a snapshot that illustrates how\nXGBoost’s output looks like. Having access to the importance of features, we can\nsimply select the top 25 features, for example, and reduce the number of columns to\nthose whose importance have been endorsed by the XGBoost model.\n0.00 0.05 0.10 0.15 0.20 0.25 0.30 0.35 0.40\nFeature importance\nWILLR_close_50\nWILLR_close_14\nFASTK\nMTM_close_14\nFASTD\nSMA_ratio_close_5_15\nRSI_ratio_close_5_15\nWVAD_50\nMA_close_28\nWILLR_close_21\nSLOWD\nRSI_close_14\nROC_close_14\nWilder_close_21\nATR_ratio_close_5_15\nVWMA_close_14\nWILLR_close_28\nRelativevolume_21\nWVAD_28\nATR_close_14\nMA_on_RSI_5_15_9\nParabolic_SAR\nBOLL_UPPER_20\nVWMA_close_28\nBOLL_LOWER_20\nFeature\nFig 1. F eature importance produced by XGBoost classifier. The figure illustrates\nthe top 25 features, ranked according to their importance produced by XGBoost for daily data\nof the S&P500 market.\n1.4 Data splitting\nBefore proceeding with auto-encoders and finishing the data preparation part, this\nresearch ensures that the auto-encoders are fed as expected. Auto-encoders expect to\nreceive an adequately correlated set of features, but current XGBoost-passed features\nare not necessarily correlated enough with each other.\nTo address this challenge, this study suggests splitting the dataset into correlated\nbunches of features. It categorizes columns into three main groups named OHLCV,\nprice-like, and non-price-like. The OHLCV group, as its name suggests, includes open,\nhigh, low, close, volume columns. The rest of the features are also split into two groups.\nBy price-like group, we refer to a group whose features’ unit is the same as price unit.\nIn a nutshell, they can be plotted on a price chart. This group may include different\nkinds of moving average indicators or any other features which are reported in dollars.\nBy contrast, the last group, a non-price-like group, has features whose units are not the\nsame as price units. This group may include oscillators like RSI and CCI, which are\ndimensionless. Since we would not like to lose any information from our primary group,\nthe OHLCV data is not passed through an auto-encoder. However, two separate\nauto-encoders are designed for both price-like and non-price-like groups to extract\nhigh-level features.\n1.5 Create Representative Dataset\nThis section provides an intuitive method to form our training dataset. Price path is\nmuch more important than the current candle information. The fact that technical\nanalysis such as candlestick patterns is all about tracking the price path is substantial\nevidence on why this study considers this step.\nMay 18, 2022 6/26\nThis research suggests defining each training instance as a set of previous\nconsecutive candles. For example, if we set training samples to consist of 24 candles, the\ndimension for every sample would be number of features ×1×24, representing the\nnumber of channels, height, and width, respectively. Fig 2 illustrates how training\ninstances are being created from the dataset. These samples will soon be used to feed\nthe auto-encoders.\nIndex Feature 1Feature 2Feature 3Feature 4... Feature N\n0\n1\n2\n...\nwindow  - 1\nwindow\nwindow + 1\nwindow + 2\n...\n2window - 1\n...\nWindowN\n1\nWidth\nChannels\n \nHeight\nFig 2. Define training instances.\n1.6 Auto-encoder\nThis part talks about the architecture of auto-encoders whose job is to extract\nhigh-level features. Their usage is not limited to feature extraction and can be employed\nto, for example, predict bankruptcy [26]. As mentioned earlier, this section is the second\nstep associated with feature engineering. The study designs two auto-encoders, one for\nprice-like features and another one for non-price-like features.\nAs their name suggests, auto-encoders are a specific type of neural network where\nthe input is the same as the output. This kind of learning is categorized as an\nunsupervised technique since they do not need explicit training labels. More precisely,\nthey are self-supervised because they generate their own labels from the training data.\nAuto-encoders attempt to reconstruct the input data such that there is a minimum\ndifference between the original input data and the reconstructed output. An\nauto-encoder consists of three components named encoder, latent-space representation,\nand decoder. The encoder compresses the input and produces the latent-space\nrepresentation, also called code. Decoder then reconstructs the input only using this\ncode. The applications of auto-encoders mainly include dimensional reduction [27],\nlatent space extraction as the high-level compressed features and anomaly detection [28].\nIt is essential to feed auto-encoders with correlated data. This paper cares about this\ncorrelation and takes some measures to correctly consider this fact. Fig 3 shows the\nmost typical version of auto-encoders, including encoder, code, and decoder.\nEven though most auto-encoders are designed as in Fig 3, this study constructs the\nauto-encoders with convolutional layers since the shape of input data requires such\nMay 18, 2022 7/26\n... ... ...\nEncoder Decoder\nCode\n... ... ...\nFig 3. Typical auto-encoder. The figure illustrates three parts of an auto-encoder. The\ninput and output data are the same as each other. The encoder layer converts the input data\ninto the code. Decoder layer also reconstructs the input data using the code. Having\nauto-encoder trained, the code, which represents the input data, is used instead of the input\ndata for further processes.\nlayers both for the encoder and for the decoder. Instead of hidden neural layers, we use\none-dimensional convolutional layers (Conv1d layers) to encode the input data and\ndecode the code. This paper uses the same auto-encoder architecture for price-like and\nnon-price-like features applied separately on their corresponding features.\n1.6.1 Encoder\nEncoder consists of Conv1d layers along with max pool and up sampling layers. The\nencoded data, red-colored in Fig 4, is the same in height and width as the input data\nand the encoder only reduces the channel size. Max pool and up sampling layers make\nauto-encoder learn better. Consequently, this paper incorporates up sampling layers in\naddition to max pool layers. More importantly, having the same dimension in width and\nheight requires us to use both max pool and up sampling layers to negate each other.\nConv 1 MaxPool 1 Conv 2 Upsample 1 Conv 3 MaxPool2\nFig 4. Encoder architecture. This figure considers the code inside the encoder layer just\nfor illustration purposes.\nDifferent arguments for Conv1d layers result in different dimensions for data. These\nlayers must ensure that dimension of the code differs only in channel size with input\ndata. This study manipulates the stride and padding arguments of Conv1d layers to\nkeep the data width constant. Eq 1 explains how these arguments relate to each other\nMay 18, 2022 8/26\nas following:\nLout =\n⌊Lin + 2∗padding−dilation∗ (kernel size− 1)− 1\nstride + 1\n⌋\n, (1)\nwhere Lout and Lin are the lengths of the output and input data to Conv1d layers,\nrespectively. The dilation is the spacing between kernel elements and is set to one by\ndefault. If stride is set to one and padding size is calculated according to Eq 2,\npadding =\n⌊kernel size− 1\n2\n⌋\n, (2)\nthe layer does not change the data width. Fig 5 provides an example of how encoder\nlayers change data dimensions.\nConv 1\n(#Features, 1, 24) (9, 1, 24)\nMaxPool 1\n(9, 1, 12)\nConv 2\n(6, 1, 12)\nUpsample 1\n(6, 1, 24)\nConv 3\n(3, 1, 24)\nMaxPool 2\n(3, 1, 12)\nFig 5. Data dimension when passing to the encoder. The figure is the encoder part\nof an auto-encoder, applied non-price-like features of S&P500 market data.\n1.6.2 Decoder\nAs for the decoder part, similar layers are used with this difference that here we\nreconstruct the code using opposite setups for our Conv1d, max pool, and up sampling\nlayers. Like the encoder part, Conv1d layers of the decoder part do not change any\ndimension but the channel size. Max pool and up sampling layers also have the same\nperformance as the encoder part. Fig 6 is the decoder architecture used in this study.\nThe only difference is that the last layer is a sequence of up sampling and Conv1d layers.\nUp sampling layers have no weights to update, and during backpropagation, there is\nnothing associated with these layers to change. As a result, ending up with these layers,\nour auto-encoder is not trained. That is why Fig 6 considers the Conv F right after the\nup sampling layer. Fig 7 provides an example of how decoder layers change data\ndimensions.\nConv 4 Upsample 2 Conv 5 MaxPool 3 Conv 6Upsample 3 & Conv F\nFig 6. Decoder architecture.\n1.7 Overview of data preparation part\nTo sum up the first part of this study, data preparation, Fig 8 provides a schematic\noverview of the sequence of steps being taken place till now. In the first part, to prevent\nconfusion between the auto-encoders learning process and the primary model’s learning\nprocess, this research did not explain how to label our training instances. However, in\nthe second part it is reviewed in detail.\nMay 18, 2022 9/26\nConv 4\n(3, 1, 12) (6, 1, 12)\nUpsample 2\n(6, 1, 24)\nConv 5\n(9, 1, 24)\nMaxPool 3 \n(9, 1, 12)\nConv 6\n(#Features, 1, 12)\nUpsample 3 & \n Conv F\n(#Features, 1, 24)\nFig 7. Data dimension when passing to the decoder. The figure shows the decoder\npart of an auto-encoder, applied non-price-like features of S&P500 market data.\nRaw OHLCV data\nFeature generation\nOHLCV data and indicators\nApplying wavelet\ntransform\nDenoised data\nFeature engineering\nusing XGBoost\nHigh level features\nData splitting\nOHLCV features\nPrice-Like features\nNon-Price-Like features\nCreate representative\ndataset\nCreate eepresentative\ndataset\nCreate representative\ndataset\nAuto-encoder one\nAuto-encoder two\nFig 8. Data preparation part overview. The\nblack-colored data is the prepared data that is ready to be fed\nto our main model.\n2 Modeling\nThe preparation of data in an accurate manner is important, but putting together a\nreliable market forecast network is equally important. Traders may have access to too\nmany data, but still cannot decide whether to buy or sell. This part ensures that there\nis a deep neural network in charge of forecasting the price movement direction for a\none-step-ahead closing price.\nSimilarly to the data preparation part, this part uses intuitions culled from financial\nmarkets to develop the model. Firstly, it explains how to label training instances. Once\ndone, it constructs the body of the deep network in accordance with intuitive reasons.\n2.1 Labeling\nThis step follows a straightforward labeling method. To label the first training instance,\nwe compare the closing price of the window-th candle to the closing price of the\n(window+1)-th candle. If the price went up, the label +1, and in the case, that price\nMay 18, 2022 10/26\nwent down the label -1 is assigned to this instance. Eq 3,\nLn =F(Pn∗window,Pn∗window+1),\nand\nF(p,p′) =Sign(p′−p\np′ ),\n(3)\nis the general formula to label training samples, where Ln∈{− 1, +1} is the label\nassigned to the n-th training instance andPi corresponds to the closing price of the\ni-th candle.\n2.2 Network architecture\nThis section introduces and designs a deep network through which binary classification\ntasks is performed. The network is divided into three elements. The first element\nincludes three separate lines of convolutional layers (Conv element), each being applied\non OHLCV, price-like, and non-price-like features. The next element is a many-to-one\nLSTM unit (LSTM element), which detects and learns the sequential patterns in data.\nFinally, two fully-connected layers (FC element) are considered to binary-classify the\ndata instances.\n2.2.1 Conv element\nBefore drilling down to the detailed construction of convolutional layers, it is worth\nreviewing why we should consider this element. We are required to design such an\nelement due to the concept of time frame in financial markets. It is important to\nbecome familiar with the tick data on financial markets to better understand time\nframes. A tick is a measure of the minimum upward or downward movement in the\nprice of a security. Each candle may contain thousands of ticks. Their corresponding\nquantity and price generally report ticks. Despite we can access the tick data, price\ncharts avoid visualizing them because tick data may exceed a hundred thousand for one\nday. Instead, they summarize a high number of tick data to one candle. This is done by\ndetermining equal intervals and aggregating all ticks within the interval to calculate\nopen, high, low, and close prices. This time interval is the time frame that we referred\nto previously. For example, when we set the time frame to one-hour, all tick data in this\ninterval is used to form its corresponding candle.\nMost of the platforms which provide us analyzing tools allow us to change this time\nframe. It could range from one-minute to one-month. The intuition is that traders do\nnot suffice on just one time frame to open a position. They may analyze BTC/USDT\ncharts on different time frames and try to find a pattern. The most important thing is\nthat after detecting a pattern, they try to give confirmation from low-frequency time\nframes like daily time frames. They may find a good-looking channel price for\nBTC/USDT in the time frame of four-hour inside which price is fluctuating between\nupper and lower lines. Suppose the price breaks out of the upper line, and breaks its\nresistance, and it seems an excellent time to open a long position in the future market\nor a buy position in the spot market. However, they do not open any position until\ngetting a strong confirmation that this breakout is not fake. One way to give the\nconfirmation is to change the time frame and observe the price position in the daily\ntime frame. Generally, financial events such as breaking out a channel price or pulling\nback to the broken resistance or support lines are more valid on low-frequency time\nframes like daily or weekly time frames.\nMay 18, 2022 11/26\nThis section considers convolutional layers whose duty is to reduce the width size of\nevery training instance. Recall that the width size is the number of consecutive candles\nthrough which we want to analyze the price path. Reducing this number is exactly like\nusing low-frequency time frames. This paper designs three separate layers containing\none max pool and two one-dimensional convolutional layers for OHLCV, price-like and\nnon-price-like data. Fig 9 shows the detailed construction of these lines. It also\nillustrates that we finally stack outputs together for the LSTM element. Fig 10 also\nshows how these layers and lines are changing the data dimension.\nConv 1 MaxPool Conv 2\nFig 9. Conv element - the first element of the model.\nThe green, red and blue colored data are OHLCV, price-like and\nnon-price-like data respectively.\nConv 1.1\n(5, 1, 24) (5, 1, 20)\nMaxPool\n(5, 1, 10)\nConv 2.1\nConv 1.2\n(3, 1, 24) (3, 1, 20)\nMaxPool\n(3, 1, 10)\nConv 2.2\nConv 1.3\n(3, 1, 24) (3, 1, 20)\nMaxPool\n(3, 1, 10)\nConv 2.3\n(5, 1, 8)\n(3, 1, 8)\n(3, 1, 8)\nStacking Together\n(11, 1, 8)\nOHLCV\nPrice-Like\nNon-Price-Like\nFig 10. Data dimension when passing to the Conv\nelement. The figure shows a Conv element, applied on training\ninstances of S&P500 market data. Reducing the width from 24\nto 8 could be considered like changing the time frame from 8h\nto daily.\nMay 18, 2022 12/26\n2.2.2 LSTM element\nIn financial markets, the price path is much more important than the current absolute\nprice. The reason is that events on previous candles may affect price behavior on the\nnext candles. When determining static or dynamic support and resistance lines, traders\nuse previous candles since they believe the information coming from previous candles\ncan be used to analyze the price fluctuations. RNNs [29,30] are designed precisely to\naddress such issues in which the information from the past is also essential for current\nprediction. Hidden states are in charge of transforming this information.\nOne of the disadvantages associated with RNNs is gradient vanishing when\nbackpropagating through time [31,32]. It causes long-term dependencies are not\ndetected. To improve the performance of RNNs to also detect long term dependencies,\nLSTM units are introduced [33]. However, LSTM is not the only way to address\nmemory problem. Gated recurrent units (GRUs), the simpler version of LSTM\nunits [34], address the same problem either. The idea behind either LSTM or GRU is to\nconsider a memory cell that determines how much information should be memorized\nand transformed to the next units. LSTM with three gates named forget gate, update\ngate, and output gate, and GRU with one gate called update gate, handle this memory\ntransformation.\nFig 10 indicates that the data sequence is not long enough to cause gradient\nvanishing. However, this paper prefers to use LSTM units to detect chronological\npatterns. It undergoes a more computational process but ensures that required\ninformation is passed to the next units as much as possible.\nCompared to RNNs, LSTM takes advantage of a memory cell c<t> to transform\ninformation. c<t> is calculated by weighting to the previous memory cell c<t−1> and a\ncandidate cell ˜c<t> which is related to the current LSTM unit. The update and forget\ngates handle the weighting task. They specify how much memory from previous units\nmust be transformed and how much information from the current unit must be\nconsidered. Having c<t> calculated, the output gate is used to calculate the current\nhidden state a<t>. Finally, a<t> is used to make a prediction. As LSTM units are\nconsecutive,a<t> and c<t> are transformed to the next LSTM unit, and this process\ncontinues until the last unit. The following equations describe the order in which each\nof the above elements is calculated:\n˜c<t> = tanh(Wc[a<t−1>,x <t>] +bc), (4)\nΓu =σ(Wu[a<t−1>,x <t>] +bu), (5)\nΓf =σ(Wf[a<t−1>,x <t>] +bf), (6)\nΓo =σ(Wo[a<t−1>,x <t>] +bo), (7)\nwhere W s and bs are weight matrices which are updated through backpropagation step\nand biases respectively. Γ u, Γf and Γo are update gate, forget gate and output gate\nrespectively. σ is also the sigmoid activation function. Using these gates along with\ncandidate cell ˜c<t>, Eq 8 and Eq 9 calculate c<t> and a<t> to be passed through the\nrest of LSTM units as following:\nc<t> = Γu◦ ˜c<t> + Γf◦c<t−1>, (8)\na<t> = Γo◦ tanh(c<t>). (9)\nMay 18, 2022 13/26\nIn each unit, the corresponding value of the forget gate determines how much\ninformation we are better to forget. If it is close to 1, the previous memory cell contains\nvaluable information from the past and should be transformed to the current memory\ncell. If it is close to 0, it means that the major part of the current memory cell is\ncalculated by the candidate cell. The Γ u, Γf and Γo are not constant for all LSTM\nunits. They are vectors containing the sigmoid output for each LSTM unit. It is worth\nmentioning that gates, hidden states, memory cells, and candidate cells are all vectors,\nso Eq 8 and Eq 9 use element-wise products between these vectors. As the last step, if\nwe wish to predict the current LSTM unit, Eq 10,\nˆy<t> = g(Wya<t> +by), (10)\nis employed to return the output where g is an activation function. Since LSTM units\nare not generally used to directly binary-classify the data instances, most of the time,\nlike in this paper, g is a softmax activation function. Fig 11 illustrates a schematic\noverview of a classic LSTM unit. There are other kinds of LSTM units such as\npeephole connections which apart from a<t−1> and x<t> considers c<t−1> to\ncalculate gates values in Eq 5, Eq 6 and Eq 7 [35]. This study takes advantage of a\nmany-to-one LSTM architecture, provided in Fig 12.\nForget Gate Update Gate Tanh Output Gate\na< t-1 >\nc< t-1 >\nx< t-1 >\nTanh\n+\na< t >\nc< t >\nOutput< t >\nFig 11. Single LSTM unit architecture.\nThe output length can vary according to the hidden states’ dimension. This\ndimension is a hyperparameter to set. This paper designs LSTM units which require the\noutput to be the same length as hidden states’ length. Fig 13 illustrates how this\nprocess happens.\n2.2.3 FC element\nAs the last element of the model, fully-connected layers binary-classify the LSTM\noutput vector. Despite its name, the layers used in this section are not really\nfully-connected since dropout layers are used to protect the model from over-fitting [36].\nTwo fully-connected layers are used to determine whether the next close price goes up\nor down. Fig 14 illustrates applying these layers to the LSTM output on actual data.\n2.3 Model quality check\nWhen it comes to financial time series data, the model is occasionally not trained at all.\nWhen back-propagating, the loss would decrease, but it is not significant to claim the\nMay 18, 2022 14/26\n1 2 L\nLSTM LSTM LSTM\nx< 1 > x< 2 > x< L >\na< 0 > a< 1 > a< 2 > a< L-1 >\nOutput\nFig 12. LSTM element - the second element of the\nmodel. x<t>,a <t> are the data sequence and hidden states\nrespectively.\nStacking Together (11, 1, 8) LSTM LSTM LSTM\n(11, ) (11, ) (11, )\nx< 1 > x< 2 > x< 8 >\n(20, )\n(20, )\na< 0 >\nOutput\nFig 13. Data dimension when passing to the LSTM\nelement. The figure shows the implementation of the LSTM\nelement on S&P500 market data. Output and hidden states\nvectors have the same length of 20.\nmodel is trained. In other words, the model loss converges too soon. For example, you\nmay consider 1000 epochs to train your model, but the model loss decreases until the\n200th epoch, and for the rest of the epochs, there is no significant reduction in model\nloss. This section will discuss how the training process can be checked.\nIn the financial time series, both model over-fitting and under-fitting are issues. The\nconcern of over-fitting is abated by training the model on the high number of data and\nusing denoisers and dropout layers in the network. This part mainly talks about an\nindex by which we can make sure our model is not under-fitted and can detect patterns.\nThe proposed index to quality check the training process is obtained by reviewing the\nloss function. Eq 11,\nL(y, ˆy) =− 1\nm(\nm∑\ni=1\nyi log ˆyi + (1−yi) log(1− ˆyi)), (11)\nis a binary cross-entropy loss function widely used in binary classification tasks where\nyi∈{ 0, 1}, ˆyi∈ (0, 1) and m are the actual label of i-th data instance, predicted label\nMay 18, 2022 15/26\nLSTM\nLSTM Output\n20\n1\n(11, )\nx< 8 >\n(20, )\nReLU\nFC 1\nSigmoid\n10\n1\nReLU\nFC 2\n10\n1\nFig 14. FC element - the third element of the model. The figure shows the\nimplementation of the FC element on S&P500 market data.\nof i-th data instance and number of data instances respectively. Through the\nbackpropagation, the loss function is supposed to decrease. The equation says, on\naverage, how wrong the model is classifying data instances.\nThis paper firstly suggests grabbing the value of the converged loss function and\nthen calculating its corresponding sigmoid value. It is obtained by using Eq 12,\nσ∗ = 10−Lc, (12)\nwhere σ∗ is the corresponding sigmoid value of the converged loss function Lc. The σ∗\nrepresents what sigmoid value, on average, the model would have if we suppose the\nwhole data as a single data instance with an actual label of 1. According to Eq 13, by\nputting a threshold on σ∗, we can figure out whether the model is trained properly:\nTraining quality =\n{\nWell-trained : if σ∗≥ζ\nUnder-fitted : if σ∗ <ζ , (13)\nwhere ζ is an optional threshold for the σ∗. This paper uses a value of between 0.8 and\n0.85 for ζ, Taking advantage of grid-searching. Suppose it is set to 0.8, equivalent to the\nloss function of 0.07 according to Eq 12. In this case, it means that if we consider all\ndata instances as a single data instance with label 1, the model classifies this single data\ninstance with the sigmoid value of 0.8, which is confident enough to claim the model is\ntrained. On the other hand, if the model loss function converges to 0.5 too soon and\ndoes not change anymore, it means that if we consider all data instances as a single data\ninstance with label 1, the model classifies this single data instance with the sigmoid\nvalue of 0.31 which is not confident at all and is a sign of model under-fitting. Forcing\nthe model to pass higher values of ζ results in over-fitting. Fig 15 illustrates a plotted\nloss function for a healthy trained model, which is neither over-fitted nor under-fitted.\nStudies typically use for-loops in the code when training the network to make the\nmodel iterate for a certain number of epochs. However, this research uses a while-loop\ninstead. Whenever the converged loss resulted in a σ∗ greater than ζ, it breaks the\nwhile-loop. Fig 16 illustrates the model training process.\nMay 18, 2022 16/26\n0 200 400 600 800\n0.0\n0.1\n0.2\n0.3\n0.4\n0.5\n0.6\n0.7\nBCE loss function value\nUnder-fitted model\nWell-trained model\nOver-fitted model\n0 200 400 600 800\nNumber of epochs\n0.2\n0.3\n0.4\n0.5\n0.6\n0.7\n0.8\n0.9\n*\nFig 15. Loss function value role to measure training\nquality . The figure shows the loss function and σ∗ values for\nthree categories of models. The green one belongs to a model\ntrained on BTC/USDT data (time frame of four-hour). The\nconverged loss function is near 0.07, which means that if we\nconsider all of the data instances as a single instance with label\n1, the model correctly predicts this instance with the Sigmoid\nvalue of 0.85.\n3 Trading strategy\nThrough data preparation and modeling parts, we classified our data instances to\npredict the next closing price. However, it does not mean the currently trained model is\nready to act on financial markets. When using Artificial intelligence (AI), we should\ncarefully map the model outputs to our needs; otherwise, the outputs are not helpful in\nour real-world problems. Every unrealistic assumption to virtually test our model’s\nperformance does not help us to detect weaknesses. While we expect a sixty-percent\naccurate model to be profitable, it may make us lose the margin. This part aims to\nintroduce a trading strategy whose essential duty is to ignore all unrealistic assumptions\nby selecting informative indicators to evaluate the model.\n3.1 Unrealistic assumptions\nOne of the drawbacks of using this model without further measurements is that it acts\non every candle. It does not make sense since no trader acts this way. Even having a\none hundred percent accurate model, acting on every candle costs a fortune for us\nMay 18, 2022 17/26\nStart\nInitialize network \n weights randomly\nCalculate loss \nfunction\n                           \nCalculate\nBack  propagate Update network\nweights\nStorage Store loss function \nvalues\n      Select X: the latest     \nN Elements \n                           \nCalculate\nIs loss converged? \nEnd\nFig 16. Model training flow chart. This paper calculates\nthe σ∗ for each epoch. If it was equal or greater than ζ, the\nlatest N loss function values(X) are retrieved from the storage.\nThen the function f decides whether the loss has converged. If\nso, it breaks the loop and returns the trained model. Function f\nconsiders the first element of X as the primary point and then\ncalculates the slope of N − 1 lines, starting from the primary\npoint and ending at other elements of X. If the average of these\nslopes is less than a threshold, it means that the loss is\nconverged. The suitable threshold is a negative value close to\nzero.\nbecause exchanges require the transaction fee for each position we wish to open. It is\nthe first unrealistic assumption that must be amended.\nThe second unrealistic assumption is that to evaluate the model performance, we use\nsome indicators such as accuracy, which considers equal weights for positions. In other\nwords, it does not matter how big the positions’ profit/loss is. For instance, positions\nwith ten percent profit are treated the same as positions with one percent profit.\nFurthermore, accuracy does not care about the positions’ margin. No matter how much\nmoney we specify to one position, it just checks whether the price direction was truly\npredicted or not. It is not close to mind since traders do not necessarily divide their\nmargin equally for their positions. It is also important for them how much profit they\nMay 18, 2022 18/26\nearn from each position. They may open eight wrong positions but still be satisfied\nsince their other two correct positions give them much more profit than the amount of\nloss coming from their wrong positions. That is why accuracy is not a solid and\ncreditable index to evaluate the model performance.\n3.1.1 Acting on every single candle\nTo deal with the first unrealistic assumption, acting on every single candle, this research\nrecommends setting a threshold for the output coming from the last sigmoid function\nprior to binary-classifying data. The sigmoid production is between 0 and 1. A common\napproach to classify the data is to consider label 0 for those instances with sigmoid\noutput lower than 0.5 and label 1 for instances with sigmoid output equal or greater\nthan 0.5. By changing this threshold, we can sift predictions with higher confidence.\nTraders may detect good entry points to open a position, but they do not risk\nopening all of them. They tend to measure an index named Risk/Reward firstly. The\nless this index [37], the more attractive the position appears for traders. The inverted\nversion of this index says how big the estimated reward (profit) is compared to the\npotential loss we undergo if we open a position. It is generally calculated by Stop loss\n(SL) and Take profit (TP) lines which traders set before opening a position. The SL is a\nprice on which traders no longer wish to undergo loss. Similarly, if the price moves\naccording to their expectation, TP is defined as an earlier price on which traders wish\nto save their profit. The Risk/Reward index is nothing but the absolute difference\nbetween entry point and SL price divided by the absolute difference between TP and\nentry point price as indicated on Eq 14. Fig 17 shows how this index is calculated\naccording to SL and TP prices.\nSL\nTP\nReward\nRisk\nEntry Point\nFig 17. Stop loss and take profit prices. Setting SL and\nTP prices is a form of art and traders use different strategies to\ndo that. This figure uses the highest and lowest prices as TP\nand SL since these prices can play a support and resistance lines\nfor this snapshot.\nRisk/Reward =|E−SL|\n|TP −E|, (14)\nwhere E is an entry point price. Traders want this index as little as possible. However,\neach of them has the desired value for this index at which they enter a position. The\nmost common value for this index is 1\n3 among traders.\nThe threshold for the sigmoid function can be determined according to the\nMay 18, 2022 19/26\nRisk/Reward index. This paper refers to this index as θ for ease of pointing. Eq 15,\nUpper = 1\n1 +θ\nLower = θ\n1 +θ\n, (15)\ndefines two thresholds for sigmoid output, named upper and lower thresholds,\nrespectively. Data instances with a sigmoid value greater than the upper threshold or\nless than the lower threshold are selected as entry points. This way, we do not act on\nthose candles with a sigmoid output of between upper and lower thresholds. Eq 16,\nSignal =\n{\nLong/Buy : if σt≥Upper\nShort/Sell : if σt≤Lower , (16)\ndescribes when this strategy opens either a long or short position where σt is the value\nof the sigmoid function corresponding to the t-th data instance. Depending on the\nvalue of θ, this strategy ignores a part of positions whose confidence is not adequate.\nConsequently, the problem of acting on each candle is addressed.\n3.1.2 Bet sizing\nTo address the second issue, specifying equal amounts of margin and weights for each\nposition, this part considers a simple approach to specify positions’ margins. By\nconsidering the absolute difference between the sigmoid function value and 0.5,\npositions’ margins are calculated. For example, if the sigmoid function value is 0.1 and\nthis number is less than the lower threshold, we specify 0.5 - 0.1 = 0.4 of our total\nmargin for this position. By increasing the lower threshold or decreasing the upper\nthreshold, we can allow our strategy to open much more positions, each having much\nless amount of margin.\n3.2 Evaluate the performance\nThere are various indexes by which the performance of models is evaluated, especially in\nour case that the model’s task is to binary-classify the data. For example, we can\ncalculate the accuracy, recall and precision indexes.\nThese indicators are related to the model outputs, not to trading strategy outputs.\nWe may have an excellent trained model that is 60 percent accurate, but it makes us\nlose money since positions’ margins and their corresponding profit/loss may not be\nequal. This model may correctly predict 60 percent of instances whose corresponding\nmargins and profits are much lower than the margins and loss of another 40 percent of\ninstances. For example, if we correctly open 60 positions with an average initial margin\nof $100 and an average profit of 4% and wrongly open 40 positions with an average\ninitial margin of 150$ and an average loss of 5%, on the whole, we lose money. In\ncontrast, a 45 percent accurate model would be profitable, hence accuracy is not a good\nindicator to determine how rich we get if we use this trained model. Although this paper\nreports the confusion matrix to show the model’s performance, it highly recommends\nusing absolute return to evaluate the trading strategy performance since we are making\nmoney from the trading strategy and not from the direct output of the model.\nResults\nSelected data to train the model are four-hour data of ETH/USDT and BTC/USDT,\neach starting from 2017 and ending in 2021, and daily data of S&P500 index beginning\nMay 18, 2022 20/26\nfrom 2001 and ending at 2021. BTC and ETH models are tested on the period of one\nyear of data, and the S&P500 model is tested on four years of data.\nThis research reports two sets of results. The first one investigates the model\nperformance and the second and more important one reports the profitability of the\nmodel.\nModel performance\nIn order to evaluate the model performance, this part reports accuracy, recall, precision,\nF1 score, converged value of loss function, and its corresponding σ∗. These indexes are\nprovided for different values of θ according to Table 2, Table 3 and Table 4.\nT able 2. Model performance - S&P500\nT able 3. Model performance - BTC/USDT\nMay 18, 2022 21/26\nT able 4. Model performance - ETH/USDT\nTrading strategy profitability\nIn order to evaluate the trading strategy profitability, this part reports the total\npercentage of profit and loss (PnL) in two conditions, without profit saving (consider\ninitial margin plus the amount of profit so far as an accessible margin) and with profit\nsaving (consider just initial margin as an accessible margin). These indicators are\nprovided for different values of θ according to Table 5, Table 6 and Table 7.\nT able 5. T rading strategy profitability - S&P500\nResults show that when we set θ on 1/4, the profitability of the trading\nstrategy decreases. The reason is that too much sensitivity about\nconfidence deprives us of the opportunity to earn positions with lower\namounts of profit.\nMay 18, 2022 22/26\nT able 6. T rading strategy profitability - BTC/USDT\nT able 7. T rading strategy profitability - ETH/USDT\nDiscussion\nThis study takes each step according to an intuition that emphasizes we need to have\ndomain knowledge of the field in which we wish to utilize artificial intelligence. This\ndomain knowledge is exactly what helps us to design each part of our research according\nto its corresponding reason in the real world.\nIntroducing a comprehensive framework that cares about all steps from manipulating\nraw data to defining a trading strategy is a novel research whose main aim is to be\nimplementable in the real world. Using traders’ behavior and coming up with\ncorresponding elements in our framework is the main edge of this research. It avoids\nsupposing unrealistic assumptions and tries to suggest solutions to help organizations,\nresearchers, or people who would like to earn profit from their financial activities.\nWith respect to all complexity in financial markets, too many other topics,\nMay 18, 2022 23/26\ncomponents, and problems have remained unexplored, and further research is required\nto address them. This research is the first attempt to adopt a compatible mindset with\nfinancial markets and define a guideline to interpret these time series data better.\nFurther research will also be considered to address and solve other obstacles we may\nencounter in financial markets.\nConclusion\nThis research provides a novel framework to manipulate financial time series data and\nexploit deep neural networks to forecast the one-step-ahead closing price. It also\nrecommends defining a trading strategy to be able to implement our work in real-world\nconditions. The first part of this study, the data preparation, consists of six important\nsteps. Firstly it generates some financial features then denoises the data. Since there is\nno evidence on how important these features are, the feature engineering part is\nconsidered as the third step. Having done that, it splits data into three categories and\ncreates a representative dataset. Finally, it uses auto-encoders to extract high-level\nfeatures and perform dimensionality reduction. The second part of this study, the\nmodeling, aims at designing an intuitive neural network architecture by which data\ninstances are classified. This part consists of three elements. The first element, the\nConv element, aims at changing data instances’ resolution to have a more robust\nprediction. The second element, the LSTM element, is designed to transform the\ninformation from the past to take the price path into account when acting on the\ncurrent candle. Finally, the FC element is considered to binary-classify the LSTM\noutputs. The last part of this study, the trading strategy, talks about how to the trained\nmodel. It mentions some unrealistic assumptions and suggests solutions to deal with\nthem. Finally, it reviews indexes and indicators that we should use to evaluate the work.\nThe performance of this framework is tested on three different pieces of data,\nincluding two coins from the cryptocurrency market and S&P500 market data. The\nresult shows that not only is this model able to provide a robust prediction, but it can\nalso provide a considerable amount of profit such that our balance would increase\n10x-12x during one year.\nReferences\n1. Chong E, Han C, Park FC. Deep learning networks for stock market analysis and\nprediction: Methodology, data representations, and case studies. Expert Systems\nwith Applications. 2017;83:187–205.\n2. Tsantekidis A, Passalis N, Tefas A, Kanniainen J, Gabbouj M, Iosifidis A. Using\ndeep learning to detect price change indications in financial markets. In: 2017\n25th European Signal Processing Conference (EUSIPCO). IEEE; 2017. p.\n2511–2515.\n3. Maknickien˙ e N, Rutkauskas AV, Maknickas A. Investigation of financial market\nprediction by recurrent neural network. Innovative Technologies for Science,\nBusiness and Education. 2011;2(11):3–8.\n4. Chen Y, Liu K, Xie Y, Hu M. Financial trading strategy system based on\nmachine learning. Mathematical Problems in Engineering. 2020;2020.\n5. Bao W, Yue J, Rao Y. A deep learning framework for financial time series using\nstacked autoencoders and long-short term memory. PloS one.\n2017;12(7):e0180944.\nMay 18, 2022 24/26\n6. Vahala J. Prediction of financial markets using Deep learning.\nMasarykUniversity, Brno, Czechia, Unpublishedmaster thesis. 2016;.\n7. Wang J, Sun T, Liu B, Cao Y, Wang D. Financial markets prediction with deep\nlearning. In: 2018 17th IEEE International Conference on Machine Learning and\nApplications (ICMLA). IEEE; 2018. p. 97–104.\n8. Hoseinzade E, Haratizadeh S, Khoeini A. U-cnnpred: A universal cnn-based\npredictor for stock markets. arXiv preprint arXiv:191112540. 2019;.\n9. Hoseinzade E, Haratizadeh S. CNNpred: CNN-based stock market prediction\nusing a diverse set of variables. Expert Systems with Applications.\n2019;129:273–285.\n10. Hoseinzade E, Haratizadeh S. CNNPred: CNN-based stock market prediction\nusing several data sources. arXiv preprint arXiv:181008923. 2018;.\n11. Samarawickrama A, Fernando T. A recurrent neural network approach in\npredicting daily stock prices an application to the Sri Lankan stock market. In:\n2017 IEEE International Conference on Industrial and Information Systems\n(ICIIS). IEEE; 2017. p. 1–6.\n12. Zanc R, Cioara T, Anghel I. Forecasting Financial Markets using Deep Learning.\nIn: 2019 IEEE 15th International Conference on Intelligent Computer\nCommunication and Processing (ICCP). IEEE; 2019. p. 459–466.\n13. Fischer T, Krauss C. Deep learning with long short-term memory networks for\nfinancial market predictions. European Journal of Operational Research.\n2018;270(2):654–669.\n14. Zhelev S, Avresky DR. Using LSTM neural network for time series predictions in\nfinancial markets. In: 2019 IEEE 18th International Symposium on Network\nComputing and Applications (NCA). IEEE; 2019. p. 1–5.\n15. Struzik ZR. Wavelet methods in (financial) time-series processing. Physica A:\nStatistical Mechanics and its Applications. 2001;296(1-2):307–319.\n16. Nobre J, Neves RF. Combining principal component analysis, discrete wavelet\ntransform and XGBoost to trade in the financial markets. Expert Systems with\nApplications. 2019;125:181–194.\n17. T¨ urkmen AC, Cemgil AT. An application of deep learning for trade signal\nprediction in financial markets. In: 2015 23nd Signal Processing and\nCommunications Applications Conference (SIU). IEEE; 2015. p. 2521–2524.\n18. Masci J, Meier U, Cire¸ san D, Schmidhuber J. Stacked convolutional\nauto-encoders for hierarchical feature extraction. In: International conference on\nartificial neural networks. Springer; 2011. p. 52–59.\n19. Ding X, Zhang Y, Liu T, Duan J. Deep learning for event-driven stock prediction.\nIn: Twenty-fourth international joint conference on artificial intelligence; 2015.\n20. Sirignano J, Cont R. Universal features of price formation in financial markets:\nperspectives from deep learning. Quantitative Finance. 2019;19(9):1449–1459.\n21. Arthur WB. Complexity in economic and financial markets. Complexity.\n1995;1(1):20–25.\nMay 18, 2022 25/26\n22. Brunnermeier M, Oehmke M, Jel G. Complexity in financial markets. Princeton\nUniversity. 2009;8.\n23. Pan Q, Zhang L, Dai G, Zhang H. Two denoising methods by wavelet transform.\nIEEE transactions on signal processing. 1999;47(12):3401–3406.\n24. Shi X, Wong YD, Li MZF, Palanisamy C, Chai C. A feature learning approach\nbased on XGBoost for driving assessment and risk prediction. Accident Analysis\n& Prevention. 2019;129:170–179.\n25. Chen T, Guestrin C. Xgboost: A scalable tree boosting system. In: Proceedings\nof the 22nd acm sigkdd international conference on knowledge discovery and data\nmining; 2016. p. 785–794.\n26. Soui M, Smiti S, Mkaouer MW, Ejbali R. Bankruptcy prediction using stacked\nauto-encoders. Applied Artificial Intelligence. 2020;34(1):80–100.\n27. Wang Y, Yao H, Zhao S. Auto-encoder based dimensionality reduction.\nNeurocomputing. 2016;184:232–242.\n28. Sakurada M, Yairi T. Anomaly detection using autoencoders with nonlinear\ndimensionality reduction. In: Proceedings of the MLSDA 2014 2nd workshop on\nmachine learning for sensory data analysis; 2014. p. 4–11.\n29. Rout AK, Dash P, Dash R, Bisoi R. Forecasting financial time series using a low\ncomplexity recurrent neural network and evolutionary learning approach. Journal\nof King Saud University-Computer and Information Sciences. 2017;29(4):536–552.\n30. Tino P, Schittenkopf C, Dorffner G. Financial volatility trading using recurrent\nneural networks. IEEE transactions on neural networks. 2001;12(4):865–874.\n31. Hochreiter S. The vanishing gradient problem during learning recurrent neural\nnets and problem solutions. International Journal of Uncertainty, Fuzziness and\nKnowledge-Based Systems. 1998;6(02):107–116.\n32. Pascanu R, Mikolov T, Bengio Y. On the difficulty of training recurrent neural\nnetworks. In: International conference on machine learning. PMLR; 2013. p.\n1310–1318.\n33. Hochreiter S, Schmidhuber J. Long short-term memory. Neural computation.\n1997;9(8):1735–1780.\n34. Chung J, Gulcehre C, Cho K, Bengio Y. Empirical evaluation of gated recurrent\nneural networks on sequence modeling. arXiv preprint arXiv:14123555. 2014;.\n35. Gers FA, Schraudolph NN, Schmidhuber J. Learning precise timing with LSTM\nrecurrent networks. Journal of machine learning research. 2002;3(Aug):115–143.\n36. Srivastava N, Hinton G, Krizhevsky A, Sutskever I, Salakhutdinov R. Dropout: a\nsimple way to prevent neural networks from overfitting. The journal of machine\nlearning research. 2014;15(1):1929–1958.\n37. Gilli M, Schumann E. Risk–reward optimisation for long-run investors: an\nempirical analysis. European Actuarial Journal. 2011;1(2):303–327.\nMay 18, 2022 26/26"
}